pyhs3/__init__.py
pyhs3/_version.py
pyhs3/_version.pyi
pyhs3/analyses.py
pyhs3/base.py
pyhs3/context.py
pyhs3/core.py
pyhs3/data.py
pyhs3/domains.py
pyhs3/exceptions.py
pyhs3/generic_parse.py
pyhs3/likelihoods.py
pyhs3/logging.py
pyhs3/metadata.py
pyhs3/networks.py
pyhs3/parameter_points.py
pyhs3/py.typed
pyhs3/distributions/__init__.py
pyhs3/distributions/basic.py
pyhs3/distributions/cms.py
pyhs3/distributions/composite.py
pyhs3/distributions/core.py
pyhs3/distributions/histogram.py
pyhs3/distributions/mathematical.py
pyhs3/distributions/physics.py
pyhs3/distributions/histfactory/__init__.py
pyhs3/distributions/histfactory/axes.py
pyhs3/distributions/histfactory/interpolations.py
pyhs3/distributions/histfactory/modifiers.py
pyhs3/distributions/histfactory/samples.py
pyhs3/functions/__init__.py
pyhs3/functions/core.py
pyhs3/functions/standard.py
pyhs3/typing/__init__.py
pyhs3/typing/aliases.py
pyhs3-0.4.0.dist-info/METADATA
pyhs3-0.4.0.dist-info/WHEEL
pyhs3-0.4.0.dist-info/licenses/LICENSE
pyhs3-0.4.0.dist-info/RECORD
