Metadata-Version: 2.4
Name: pyhs3
Version: 0.4.0
Summary: pure-Python HS3 implementation with tensors and autodiff
Project-URL: Homepage, https://github.com/scipp-atlas/pyhs3
Project-URL: Bug Tracker, https://github.com/scipp-atlas/pyhs3/issues
Project-URL: Discussions, https://github.com/scipp-atlas/pyhs3/discussions
Project-URL: Changelog, https://github.com/scipp-atlas/pyhs3/releases
Author-email: Giordon Stark <kratsg@gmail.com>
License: 
License-File: LICENSE
Classifier: Development Status :: 1 - Planning
Classifier: Intended Audience :: Developers
Classifier: Intended Audience :: Science/Research
Classifier: License :: OSI Approved :: Apache Software License
Classifier: Operating System :: OS Independent
Classifier: Programming Language :: Python
Classifier: Programming Language :: Python :: 3
Classifier: Programming Language :: Python :: 3 :: Only
Classifier: Programming Language :: Python :: 3.10
Classifier: Programming Language :: Python :: 3.11
Classifier: Programming Language :: Python :: 3.12
Classifier: Programming Language :: Python :: 3.13
Classifier: Topic :: Scientific/Engineering
Classifier: Typing :: Typed
Requires-Python: >=3.10
Requires-Dist: numpy
Requires-Dist: pydantic
Requires-Dist: pytensor>=2.33.0
Requires-Dist: rich
Requires-Dist: rustworkx
Requires-Dist: sympy
Provides-Extra: dev
Requires-Dist: pytest-cov>=3; extra == 'dev'
Requires-Dist: pytest>=6; extra == 'dev'
Requires-Dist: tbump>=6.7.0; extra == 'dev'
Provides-Extra: docs
Requires-Dist: furo>=2023.08.17; extra == 'docs'
Requires-Dist: intersphinx-registry>=0.2411.17; extra == 'docs'
Requires-Dist: ipywidgets; extra == 'docs'
Requires-Dist: myst-parser>=0.13; extra == 'docs'
Requires-Dist: sphinx-autodoc-typehints; extra == 'docs'
Requires-Dist: sphinx-click; extra == 'docs'
Requires-Dist: sphinx-copybutton!=0.5.1,>=0.3.2; extra == 'docs'
Requires-Dist: sphinx-issues; extra == 'docs'
Requires-Dist: sphinx>=7.0; extra == 'docs'
Requires-Dist: sphinxcontrib-mermaid; extra == 'docs'
Provides-Extra: test
Requires-Dist: pydocstyle; extra == 'test'
Requires-Dist: pydot; extra == 'test'
Requires-Dist: pyhf>=0.7.6; extra == 'test'
Requires-Dist: pytest-cov>=3; extra == 'test'
Requires-Dist: pytest>=6; extra == 'test'
Requires-Dist: scikit-hep-testdata>=0.5.7; extra == 'test'
